bfastor/__init__.py
bfastor/core.py
bfastor/helpers.py
bfastor/jax_gmm.py
bfastor/loss.py
bfastor/maps.py
bfastor/models.py
bfastor/profiling.py
bfastor/spatial.py
bfastor/blur/__init__.py
bfastor/blur/atom_parameters.py
bfastor/blur/isp.py
bfastor/blur/log_mvg.py
bfastor/blur/log_sp.py
bfastor/blur/mvg.py
bfastor/blur/simulate_map.py
bfastor/blur/sp.py
bfastor/blur/utils.py
bfastor/scripts/__init__.py
bfastor/scripts/refine_bfactors.py
bfastor-0.2.0.dist-info/LICENSE.txt
bfastor-0.2.0.dist-info/METADATA
bfastor-0.2.0.dist-info/WHEEL
bfastor-0.2.0.dist-info/entry_points.txt
bfastor-0.2.0.dist-info/top_level.txt
bfastor-0.2.0.dist-info/RECORD
