Metadata-Version: 2.1
Name: bfastor
Version: 0.2.0
Summary: Fast cryo-EM B-factor refinement
Author-email: Joseph Beton <joseph.beton@cssb-hamburg.de>
Maintainer-email: Joseph Beton <joseph.beton@cssb-hamburg.de>
Project-URL: Homepage, https://gitlab.com/topf-lab/jaxref
Project-URL: Bug Reports, https://gitlab.com/topf-lab/jaxref/issues
Project-URL: Source, https://gitlab.com/topf-lab/jaxref/
Classifier: Development Status :: 3 - Alpha
Classifier: Intended Audience :: Science/Research
Classifier: Programming Language :: Python :: 3
Classifier: Programming Language :: Python :: 3.9
Classifier: Programming Language :: Python :: 3.10
Classifier: Programming Language :: Python :: 3.11
Classifier: Programming Language :: Python :: 3 :: Only
Requires-Python: >=3.9
License-File: LICENSE.txt
Requires-Dist: chex>=0.1.85
Requires-Dist: jax>=0.4.30
Requires-Dist: optax>=0.1
Requires-Dist: flax>=0.8
Requires-Dist: numpy>=1.17
Requires-Dist: pandas>=2.2
Requires-Dist: gemmi>=0.5.8
Requires-Dist: mrcfile>=1.5
Requires-Dist: ratelimit>=2.2
Requires-Dist: voxcov>=0.2.8
Requires-Dist: matplotlib>=3.6
Requires-Dist: tqdm>=4.0
Provides-Extra: cuda12
Requires-Dist: jax[cuda12]; extra == "cuda12"
Provides-Extra: dev
Requires-Dist: check-manifest; extra == "dev"
Requires-Dist: pytest; extra == "dev"
Requires-Dist: black; extra == "dev"
Provides-Extra: test
Requires-Dist: coverage; extra == "test"
Requires-Dist: pytest; extra == "test"
